Workbook

Sheet Product Categories
A1: ZAVA SMART FABRIC & ATHLETIC WEAR - 2025 YTD SALES REPORT
A3: Month | B3: Category | C3: Product | D3: Units Sold | E3: Unit Price ($) | F3: Revenue ($) | G3: Gross Profit ($)
A4: Oct 2024 | B4: Smart Fabric | C4: Smart Athletic Shirts | D4: 2929 | E4: 129.99 | F4: 437351.4 | G4: 227422.73
A5: Oct 2024 | B5: Smart Fabric | C5: Performance Monitoring Leggings | D5: 1904 | E5: 159.99 | F5: 349913.73 | G5: 181955.14
A6: Oct 2024 | B6: Smart Fabric | C6: Temperature-Regulating Shorts | D6: 3046 | E6: 89.99 | F6: 314865.7 | G6: 163730.16
A7: Oct 2024 | B7: Smart Fabric | C7: Biometric Sports Bras | D7: 2856 | E7: 79.99 | F7: 262418.89 | G7: 136457.83
A8: Oct 2024 | B8: Smart Fabric | C8: Zava Smart Fiber | D8: 2431 | E8: 229 | F8: 639472.16 | G8: 358104.41
A9: Oct 2024 | B9: Smart Fabric | C9: AI-Enhanced Running Socks | D9: 3809 | E9: 39.99 | F9: 174969.99 | G9: 90984.397
A10: Oct 2024 | B10: Traditional Athletic Wear | C10: Basic Athletic Shirts | D10: 5470 | E10: 29.99 | F10: 188436.48 | G10: 67837.135
A11: Oct 2024 | B11: Traditional Athletic Wear | C11: Standard Leggings | D11: 2953 | E11: 49.99 | F11: 169569.52 | G11: 61045.027
A12: Oct 2024 | B12: Traditional Athletic Wear | C12: Athletic Shorts | D12: 3516 | E12: 34.99 | F12: 141316.87 | G12: 50874.073
A13: Oct 2024 | B13: Traditional Athletic Wear | C13: Sports Bras | D13: 3938 | E13: 24.99 | F13: 113042.87 | G13: 40695.433
A14: Oct 2024 | B14: Traditional Athletic Wear | C14: Compression Wear | D14: 1367 | E14: 59.99 | F14: 94199.496 | G14: 33911.819
A15: Oct 2024 | B15: Traditional Athletic Wear | C15: Athletic Socks | D15: 9471 | E15: 12.99 | F15: 141320.83 | G15: 50875.5
... A42: Dec 2024 | B42: Traditional Athletic Wear | C42: Accessories & Equipment | D42: 4838 | E42: 19.99 | F42: 96711.62 | G42: 34816.183
A43: =DATE(2025,1,1) -> 45658 | B43: Smart Fabric | C43: Smart Athletic Shirts | D43: 4106 | E43: 129.99 | F43: 533738.94 | G43: 277544.25
A44: =DATE(2025,1,1) -> 45658 | B44: Smart Fabric | C44: Performance Monitoring Leggings | D44: 2669 | E44: 159.99 | F44: 427013.31 | G44: 222046.92
A45: =DATE(2025,1,1) -> 45658 | B45: Smart Fabric | C45: Temperature-Regulating Shorts | D45: 4270 | E45: 89.99 | F45: 384257.3 | G45: 199813.8
A46: =DATE(2025,1,1) -> 45658 | B46: Smart Fabric | C46: Biometric Sports Bras | D46: 4004 | E46: 79.99 | F46: 320279.96 | G46: 166545.58
A47: =DATE(2025,1,1) -> 45658 | B47: Smart Fabric | C47: Zava Smart Fiber | D47: 3406 | E47: 229 | F47: 779974 | G47: 436785.44
A48: =DATE(2025,1,1) -> 45658 | B48: Smart Fabric | C48: AI-Enhanced Running Socks | D48: 5339 | E48: 39.99 | F48: 213506.61 | G48: 111023.44
A49: =DATE(2025,1,1) -> 45658 | B49: Traditional Athletic Wear | C49: Basic Athletic Shirts | D49: 7667 | E49: 29.99 | F49: 229933.33 | G49: 82775.999
A50: =DATE(2025,1,1) -> 45658 | B50: Traditional Athletic Wear | C50: Standard Leggings | D50: 4139 | E50: 49.99 | F50: 206908.61 | G50: 74487.1
A51: =DATE(2025,1,1) -> 45658 | B51: Traditional Athletic Wear | C51: Athletic Shorts | D51: 4928 | E51: 34.99 | F51: 172430.72 | G51: 62075.059
A52: =DATE(2025,1,1) -> 45658 | B52: Traditional Athletic Wear | C52: Sports Bras | D52: 5520 | E52: 24.99 | F52: 137944.8 | G52: 49660.128
A53: =DATE(2025,1,1) -> 45658 | B53: Traditional Athletic Wear | C53: Compression Wear | D53: 1916 | E53: 59.99 | F53: 114940.84 | G53: 41378.702
A54: =DATE(2025,1,1) -> 45658 | B54: Traditional Athletic Wear | C54: Athletic Socks | D54: 13276 | E54: 12.99 | F54: 172455.24 | G54: 62083.886
A55: =DATE(2025,1,1) -> 45658 | B55: Traditional Athletic Wear | C55: Accessories & Equipment | D55: 5751 | E55: 19.99 | F55: 114962.49 | G55: 41386.496
A56: =DATE(2025,2,1) -> 45689 | B56: Smart Fabric | C56: Smart Athletic Shirts | D56: 4171 | E56: 129.99 | F56: 542188.29 | G56: 281937.91
A57: =DATE(2025,2,1) -> 45689 | B57: Smart Fabric | C57: Performance Monitoring Leggings | D57: 2711 | E57: 159.99 | F57: 433732.89 | G57: 225541.1
A58: =DATE(2025,2,1) -> 45689 | B58: Smart Fabric | C58: Temperature-Regulating Shorts | D58: 4338 | E58: 89.99 | F58: 390376.62 | G58: 202995.84
A59: =DATE(2025,2,1) -> 45689 | B59: Smart Fabric | C59: Biometric Sports Bras | D59: 4067 | E59: 79.99 | F59: 325319.33 | G59: 169166.05
A60: =DATE(2025,2,1) -> 45689 | B60: Smart Fabric | C60: Zava Smart Fiber | D60: 3459 | E60: 229 | F60: 792111 | G60: 443582.16
A61: =DATE(2025,2,1) -> 45689 | B61: Smart Fabric | C61: AI-Enhanced Running Socks | D61: 5424 | E61: 39.99 | F61: 216905.76 | G61: 112791
A62: =DATE(2025,2,1) -> 45689 | B62: Traditional Athletic Wear | C62: Basic Athletic Shirts | D62: 7789 | E62: 29.99 | F62: 233592.11 | G62: 84093.16
A63: =DATE(2025,2,1) -> 45689 | B63: Traditional Athletic Wear | C63: Standard Leggings | D63: 4205 | E63: 49.99 | F63: 210207.95 | G63: 75674.862
A64: =DATE(2025,2,1) -> 45689 | B64: Traditional Athletic Wear | C64: Athletic Shorts | D64: 5007 | E64: 34.99 | F64: 175194.93 | G64: 63070.175
A65: =DATE(2025,2,1) -> 45689 | B65: Traditional Athletic Wear | C65: Sports Bras | D65: 5608 | E65: 24.99 | F65: 140143.92 | G65: 50451.811
A66: =DATE(2025,2,1) -> 45689 | B66: Traditional Athletic Wear | C66: Compression Wear | D66: 1947 | E66: 59.99 | F66: 116800.53 | G66: 42048.191
A67: =DATE(2025,2,1) -> 45689 | B67: Traditional Athletic Wear | C67: Athletic Socks | D67: 13487 | E67: 12.99 | F67: 175196.13 | G67: 63070.607
A68: =DATE(2025,2,1) -> 45689 | B68: Traditional Athletic Wear | C68: Accessories & Equipment | D68: 5843 | E68: 19.99 | F68: 116801.57 | G68: 42048.565
A69: =DATE(2025,3,1) -> 45717 | B69: Smart Fabric | C69: Smart Athletic Shirts | D69: 4672 | E69: 129.99 | F69: 607313.28 | G69: 315802.91
A70: =DATE(2025,3,1) -> 45717 | B70: Smart Fabric | C70: Performance Monitoring Leggings | D70: 3036 | E70: 159.99 | F70: 485729.64 | G70: 252579.41
A71: =DATE(2025,3,1) -> 45717 | B71: Smart Fabric | C71: Temperature-Regulating Shorts | D71: 4859 | E71: 89.99 | F71: 437261.41 | G71: 227375.93
A72: =DATE(2025,3,1) -> 45717 | B72: Smart Fabric | C72: Biometric Sports Bras | D72: 4555 | E72: 79.99 | F72: 364354.45 | G72: 189464.31
A73: =DATE(2025,3,1) -> 45717 | B73: Smart Fabric | C73: Zava Smart Fiber | D73: 3874 | E73: 229 | F73: 887146 | G73: 496801.76
A74: =DATE(2025,3,1) -> 45717 | B74: Smart Fabric | C74: AI-Enhanced Running Socks | D74: 6074 | E74: 39.99 | F74: 242899.26 | G74: 126307.62
A75: =DATE(2025,3,1) -> 45717 | B75: Traditional Athletic Wear | C75: Basic Athletic Shirts | D75: 8723 | E75: 29.99 | F75: 261602.77 | G75: 94176.997
A76: =DATE(2025,3,1) -> 45717 | B76: Traditional Athletic Wear | C76: Standard Leggings | D76: 4710 | E76: 49.99 | F76: 235452.9 | G76: 84763.044
A77: =DATE(2025,3,1) -> 45717 | B77: Traditional Athletic Wear | C77: Athletic Shorts | D77: 5607 | E77: 34.99 | F77: 196188.93 | G77: 70628.015
A78: =DATE(2025,3,1) -> 45717 | B78: Traditional Athletic Wear | C78: Sports Bras | D78: 6281 | E78: 24.99 | F78: 156962.19 | G78: 56506.388
A79: =DATE(2025,3,1) -> 45717 | B79: Traditional Athletic Wear | C79: Compression Wear | D79: 2180 | E79: 59.99 | F79: 130778.2 | G79: 47080.152
A80: =DATE(2025,3,1) -> 45717 | B80: Traditional Athletic Wear | C80: Athletic Socks | D80: 15105 | E80: 12.99 | F80: 196213.95 | G80: 70637.022
A81: =DATE(2025,3,1) -> 45717 | B81: Traditional Athletic Wear | C81: Accessories & Equipment | D81: 6543 | E81: 19.99 | F81: 130794.57 | G81: 47086.045
A82: =DATE(2025,4,1) -> 45748 | B82: Smart Fabric | C82: Smart Athletic Shirts | D82: 4672 | E82: =_xlfn.XLOOKUP(C82,$C:$C,$E:$E) -> 129.99 | F82: 619459.55 | G82: 322118.96
A83: =DATE(2025,4,1) -> 45748 | B83: Smart Fabric | C83: Performance Monitoring Leggings | D83: 3036 | E83: =_xlfn.XLOOKUP(C83,$C:$C,$E:$E) -> 159.99 | F83: 495444.23 | G83: 257631
A84: =DATE(2025,4,1) -> 45748 | B84: Smart Fabric | C84: Temperature-Regulating Shorts | D84: 4859 | E84: =_xlfn.XLOOKUP(C84,$C:$C,$E:$E) -> 89.99 | F84: 446006.64 | G84: 231923.45
A85: =DATE(2025,4,1) -> 45748 | B85: Smart Fabric | C85: Biometric Sports Bras | D85: 4555 | E85: =_xlfn.XLOOKUP(C85,$C:$C,$E:$E) -> 79.99 | F85: 371641.54 | G85: 193253.6
A86: =DATE(2025,4,1) -> 45748 | B86: Smart Fabric | C86: Zava Smart Fiber | D86: 3874 | E86: =_xlfn.XLOOKUP(C86,$C:$C,$E:$E) -> 229 | F86: 904888.92 | G86: 506737.8
A87: =DATE(2025,4,1) -> 45748 | B87: Smart Fabric | C87: AI-Enhanced Running Socks | D87: 6074 | E87: =_xlfn.XLOOKUP(C87,$C:$C,$E:$E) -> 39.99 | F87: 247757.25 | G87: 128833.77
A88: =DATE(2025,4,1) -> 45748 | B88: Traditional Athletic Wear | C88: Basic Athletic Shirts | D88: 8723 | E88: =_xlfn.XLOOKUP(C88,$C:$C,$E:$E) -> 29.99 | F88: 266834.83 | G88: 96060.537
A89: =DATE(2025,4,1) -> 45748 | B89: Traditional Athletic Wear | C89: Standard Leggings | D89: 4710 | E89: =_xlfn.XLOOKUP(C89,$C:$C,$E:$E) -> 49.99 | F89: 240161.96 | G89: 86458.305
A90: =DATE(2025,4,1) -> 45748 | B90: Traditional Athletic Wear | C90: Athletic Shorts | D90: 5607 | E90: =_xlfn.XLOOKUP(C90,$C:$C,$E:$E) -> 34.99 | F90: 200112.71 | G90: 72040.575
A91: =DATE(2025,4,1) -> 45748 | B91: Traditional Athletic Wear | C91: Sports Bras | D91: 6281 | E91: =_xlfn.XLOOKUP(C91,$C:$C,$E:$E) -> 24.99 | F91: 160101.43 | G91: 57636.516
A92: =DATE(2025,4,1) -> 45748 | B92: Traditional Athletic Wear | C92: Compression Wear | D92: 2180 | E92: =_xlfn.XLOOKUP(C92,$C:$C,$E:$E) -> 59.99 | F92: 133393.76 | G92: 48021.755
A93: =DATE(2025,4,1) -> 45748 | B93: Traditional Athletic Wear | C93: Athletic Socks | D93: 15105 | E93: =_xlfn.XLOOKUP(C93,$C:$C,$E:$E) -> 12.99 | F93: 200138.23 | G93: 72049.762
A94: =DATE(2025,4,1) -> 45748 | B94: Traditional Athletic Wear | C94: Accessories & Equipment | D94: 6543 | E94: =_xlfn.XLOOKUP(C94,$C:$C,$E:$E) -> 19.99 | F94: 133410.46 | G94: 48027.766
A95: =DATE(2025,5,1) -> 45778 | B95: Smart Fabric | C95: Smart Athletic Shirts | D95: 4672 | E95: =_xlfn.XLOOKUP(C95,$C:$C,$E:$E) -> 129.99 | F95: 631848.74 | G95: 328561.34
A96: =DATE(2025,5,1) -> 45778 | B96: Smart Fabric | C96: Performance Monitoring Leggings | D96: 3036 | E96: =_xlfn.XLOOKUP(C96,$C:$C,$E:$E) -> 159.99 | F96: 505353.12 | G96: 262783.62
A97: =DATE(2025,5,1) -> 45778 | B97: Smart Fabric | C97: Temperature-Regulating Shorts | D97: 4859 | E97: =_xlfn.XLOOKUP(C97,$C:$C,$E:$E) -> 89.99 | F97: 454926.77 | G97: 236561.92
A98: =DATE(2025,5,1) -> 45778 | B98: Smart Fabric | C98: Biometric Sports Bras | D98: 4555 | E98: =_xlfn.XLOOKUP(C98,$C:$C,$E:$E) -> 79.99 | F98: 379074.37 | G98: 197118.67
A99: =DATE(2025,5,1) -> 45778 | B99: Smart Fabric | C99: Zava Smart Fiber | D99: 3874 | E99: =_xlfn.XLOOKUP(C99,$C:$C,$E:$E) -> 229 | F99: 922986.7 | G99: 516872.55
A100: =DATE(2025,5,1) -> 45778 | B100: Smart Fabric | C100: AI-Enhanced Running Socks | D100: 6074 | E100: =_xlfn.XLOOKUP(C100,$C:$C,$E:$E) -> 39.99 | F100: 252712.39 | G100: 131410.44
A101: =DATE(2025,5,1) -> 45778 | B101: Traditional Athletic Wear | C101: Basic Athletic Shirts | D101: 8723 | E101: =_xlfn.XLOOKUP(C101,$C:$C,$E:$E) -> 29.99 | F101: 272171.52 | G101: 97981.748
A102: =DATE(2025,5,1) -> 45778 | B102: Traditional Athletic Wear | C102: Standard Leggings | D102: 4710 | E102: =_xlfn.XLOOKUP(C102,$C:$C,$E:$E) -> 49.99 | F102: 244965.2 | G102: 88187.471
A103: =DATE(2025,5,1) -> 45778 | B103: Traditional Athletic Wear | C103: Athletic Shorts | D103: 5607 | E103: =_xlfn.XLOOKUP(C103,$C:$C,$E:$E) -> 34.99 | F103: 204114.96 | G103: 73481.387
A104: =DATE(2025,5,1) -> 45778 | B104: Traditional Athletic Wear | C104: Sports Bras | D104: 6281 | E104: =_xlfn.XLOOKUP(C104,$C:$C,$E:$E) -> 24.99 | F104: 163303.46 | G104: 58789.246
A105: =DATE(2025,5,1) -> 45778 | B105: Traditional Athletic Wear | C105: Compression Wear | D105: 2180 | E105: =_xlfn.XLOOKUP(C105,$C:$C,$E:$E) -> 59.99 | F105: 136061.64 | G105: 48982.19
A106: =DATE(2025,5,1) -> 45778 | B106: Traditional Athletic Wear | C106: Athletic Socks | D106: 15105 | E106: =_xlfn.XLOOKUP(C106,$C:$C,$E:$E) -> 12.99 | F106: 204140.99 | G106: 73490.758
A107: =DATE(2025,5,1) -> 45778 | B107: Traditional Athletic Wear | C107: Accessories & Equipment | D107: 6543 | E107: =_xlfn.XLOOKUP(C107,$C:$C,$E:$E) -> 19.99 | F107: 136078.67 | G107: 48988.321
A108: =DATE(2025,6,1) -> 45809 | B108: Smart Fabric | C108: Smart Athletic Shirts | D108: 4672 | E108: =_xlfn.XLOOKUP(C108,$C:$C,$E:$E) -> 129.99 | F108: 644485.71 | G108: 335132.57
A109: =DATE(2025,6,1) -> 45809 | B109: Smart Fabric | C109: Performance Monitoring Leggings | D109: 3036 | E109: =_xlfn.XLOOKUP(C109,$C:$C,$E:$E) -> 159.99 | F109: 515460.18 | G109: 268039.29
A110: =DATE(2025,6,1) -> 45809 | B110: Smart Fabric | C110: Temperature-Regulating Shorts | D110: 4859 | E110: =_xlfn.XLOOKUP(C110,$C:$C,$E:$E) -> 89.99 | F110: 464025.31 | G110: 241293.16
A111: =DATE(2025,6,1) -> 45809 | B111: Smart Fabric | C111: Biometric Sports Bras | D111: 4555 | E111: =_xlfn.XLOOKUP(C111,$C:$C,$E:$E) -> 79.99 | F111: 386655.86 | G111: 201061.05
A112: =DATE(2025,6,1) -> 45809 | B112: Smart Fabric | C112: Zava Smart Fiber | D112: 3874 | E112: =_xlfn.XLOOKUP(C112,$C:$C,$E:$E) -> 229 | F112: 941446.43 | G112: 527210
A113: =DATE(2025,6,1) -> 45809 | B113: Smart Fabric | C113: AI-Enhanced Running Socks | D113: 6074 | E113: =_xlfn.XLOOKUP(C113,$C:$C,$E:$E) -> 39.99 | F113: 257766.64 | G113: 134038.65
A114: =DATE(2025,6,1) -> 45809 | B114: Traditional Athletic Wear | C114: Basic Athletic Shirts | D114: 8723 | E114: =_xlfn.XLOOKUP(C114,$C:$C,$E:$E) -> 29.99 | F114: 277614.95 | G114: 99941.383
A115: =DATE(2025,6,1) -> 45809 | B115: Traditional Athletic Wear | C115: Standard Leggings | D115: 4710 | E115: =_xlfn.XLOOKUP(C115,$C:$C,$E:$E) -> 49.99 | F115: 249864.5 | G115: 89951.22
A116: =DATE(2025,6,1) -> 45809 | B116: Traditional Athletic Wear | C116: Athletic Shorts | D116: 5607 | E116: =_xlfn.XLOOKUP(C116,$C:$C,$E:$E) -> 34.99 | F116: 208197.26 | G116: 74951.014
A117: =DATE(2025,6,1) -> 45809 | B117: Traditional Athletic Wear | C117: Sports Bras | D117: 6281 | E117: =_xlfn.XLOOKUP(C117,$C:$C,$E:$E) -> 24.99 | F117: 166569.53 | G117: 59965.031
A118: =DATE(2025,6,1) -> 45809 | B118: Traditional Athletic Wear | C118: Compression Wear | D118: 2180 | E118: =_xlfn.XLOOKUP(C118,$C:$C,$E:$E) -> 59.99 | F118: 138782.87 | G118: 49961.834
A119: =DATE(2025,6,1) -> 45809 | B119: Traditional Athletic Wear | C119: Athletic Socks | D119: 15105 | E119: =_xlfn.XLOOKUP(C119,$C:$C,$E:$E) -> 12.99 | F119: 208223.81 | G119: 74960.573
A120: =DATE(2025,6,1) -> 45809 | B120: Traditional Athletic Wear | C120: Accessories & Equipment | D120: 6543 | E120: =_xlfn.XLOOKUP(C120,$C:$C,$E:$E) -> 19.99 | F120: 138800.24 | G120: 49968.088
A121: =DATE(2025,7,1) -> 45839 | B121: Smart Fabric | C121: Smart Athletic Shirts | D121: 4672 | E121: =_xlfn.XLOOKUP(C121,$C:$C,$E:$E) -> 129.99 | F121: 657375.43 | G121: 341835.22
A122: =DATE(2025,7,1) -> 45839 | B122: Smart Fabric | C122: Performance Monitoring Leggings | D122: 3036 | E122: =_xlfn.XLOOKUP(C122,$C:$C,$E:$E) -> 159.99 | F122: 525769.38 | G122: 273400.08
A123: =DATE(2025,7,1) -> 45839 | B123: Smart Fabric | C123: Temperature-Regulating Shorts | D123: 4859 | E123: =_xlfn.XLOOKUP(C123,$C:$C,$E:$E) -> 89.99 | F123: 473305.81 | G123: 246119.02
A124: =DATE(2025,7,1) -> 45839 | B124: Smart Fabric | C124: Biometric Sports Bras | D124: 4555 | E124: =_xlfn.XLOOKUP(C124,$C:$C,$E:$E) -> 79.99 | F124: 394388.97 | G124: 205082.27
A125: =DATE(2025,7,1) -> 45839 | B125: Smart Fabric | C125: Zava Smart Fiber | D125: 3874 | E125: =_xlfn.XLOOKUP(C125,$C:$C,$E:$E) -> 229 | F125: 960275.36 | G125: 537754.2
A126: =DATE(2025,7,1) -> 45839 | B126: Smart Fabric | C126: AI-Enhanced Running Socks | D126: 6074 | E126: =_xlfn.XLOOKUP(C126,$C:$C,$E:$E) -> 39.99 | F126: 262921.97 | G126: 136719.42
A127: =DATE(2025,7,1) -> 45839 | B127: Traditional Athletic Wear | C127: Basic Athletic Shirts | D127: 8723 | E127: =_xlfn.XLOOKUP(C127,$C:$C,$E:$E) -> 29.99 | F127: 283167.25 | G127: 101940.21
...

Sheet Regional Sales
A1: ZAVA SMART FABRIC & ATHLETIC WEAR - 2025 YTD SALES REPORT
A3: Month | B3: Region | C3: Total Revenue ($) | D3: Smart Fabric Revenue ($) | E3: Traditional Revenue ($) | F3: Smart Fabric % | G3: Customers
A4: 45383 | B4: North America | C4: 1924048 | D4: 1385315 | E4: 538733 | F4: 0.72 | G4: 22636
A5: 45383 | B5: Europe | C5: 1087505 | D5: 674253 | E5: 413252 | F5: 0.62 | G5: 12794
A6: 45383 | B6: Asia Pacific | C6: 1003851 | D6: 803081 | E6: 200770 | F6: 0.8 | G6: 15444
A7: 45383 | B7: Other Markets | C7: 167309 | D7: 73616 | E7: 93693 | F7: 0.44 | G7: 2574
A8: 45413 | B8: North America | C8: 1952909 | D8: 1406094 | E8: 546815 | F8: 0.72 | G8: 22975
A9: 45413 | B9: Europe | C9: 1103818 | D9: 684367 | E9: 419451 | F9: 0.62 | G9: 12986
A10: 45413 | B10: Asia Pacific | C10: 1018909 | D10: 815127 | E10: 203782 | F10: 0.8 | G10: 15676
A11: 45413 | B11: Other Markets | C11: 169818 | D11: 74720 | E11: 95098 | F11: 0.44 | G11: 2613
A12: 45444 | B12: North America | C12: 1982203 | D12: 1427186 | E12: 555017 | F12: 0.72 | G12: 23320
A13: 45444 | B13: Europe | C13: 1120375 | D13: 694633 | E13: 425742 | F13: 0.62 | G13: 13181
A14: 45444 | B14: Asia Pacific | C14: 1034193 | D14: 827354 | E14: 206839 | F14: 0.8 | G14: 15911
A15: 45444 | B15: Other Markets | C15: 172365 | D15: 75841 | E15: 96524 | F15: 0.44 | G15: 2652
... A48: 45717 | B48: North America | C48: 1993040.9 | D48: 1474850.2 | E48: 518190.63 | F48: 0.74 | G48: 23448
A49: =DATE(2025,3,1) -> 45717 | B49: Europe | C49: 1126501.4 | D49: 720960.87 | E49: 405540.49 | F49: 0.64 | G49: 13253
A50: =DATE(2025,3,1) -> 45717 | B50: Asia Pacific | C50: 1039847.4 | D50: 852674.88 | E50: 187172.53 | F50: 0.82 | G50: 15998
A51: =DATE(2025,3,1) -> 45717 | B51: Other Markets | C51: 173307.9 | D51: 79721.635 | E51: 93586.267 | F51: 0.46 | G51: 2666
A52: =DATE(2025,4,1) -> 45748 | B52: North America | C52: 2032901.7 | D52: 1504347.3 | E52: 528554.44 | F52: 0.74 | G52: 23916
A53: =DATE(2025,4,1) -> 45748 | B53: Europe | C53: 1149031.4 | D53: 735380.09 | E53: 413651.3 | F53: 0.64 | G53: 13518
A54: =DATE(2025,4,1) -> 45748 | B54: Asia Pacific | C54: 1060644.4 | D54: 869728.38 | E54: 190915.98 | F54: 0.82 | G54: 16318
A55: =DATE(2025,4,1) -> 45748 | B55: Other Markets | C55: 176774.06 | D55: 81316.068 | E55: 95457.992 | F55: 0.46 | G55: 2720
A56: =DATE(2025,5,1) -> 45778 | B56: North America | C56: 2073559.7 | D56: 1534434.2 | E56: 539125.53 | F56: 0.74 | G56: 24395
A57: =DATE(2025,5,1) -> 45778 | B57: Europe | C57: 1172012 | D57: 750087.69 | E57: 421924.33 | F57: 0.64 | G57: 13788
A58: =DATE(2025,5,1) -> 45778 | B58: Asia Pacific | C58: 1081857.2 | D58: 887122.94 | E58: 194734.3 | F58: 0.82 | G58: 16644
A59: =DATE(2025,5,1) -> 45778 | B59: Other Markets | C59: 180309.54 | D59: 82942.389 | E59: 97367.152 | F59: 0.46 | G59: 2774
A60: =DATE(2025,6,1) -> 45809 | B60: North America | C60: 2115030.9 | D60: 1565122.9 | E60: 549908.04 | F60: 0.74 | G60: 24883
A61: =DATE(2025,6,1) -> 45809 | B61: Europe | C61: 1195452.3 | D61: 765089.45 | E61: 430362.81 | F61: 0.64 | G61: 14064
A62: =DATE(2025,6,1) -> 45809 | B62: Asia Pacific | C62: 1103494.4 | D62: 904865.4 | E62: 198628.99 | F62: 0.82 | G62: 16977
A63: =DATE(2025,6,1) -> 45809 | B63: Other Markets | C63: 183915.73 | D63: 84601.237 | E63: 99314.495 | F63: 0.46 | G63: 2829
A64: =DATE(2025,7,1) -> 45839 | B64: North America | C64: 2157331.5 | D64: 1596425.3 | E64: 560906.2 | F64: 0.74 | G64: 25380
A65: =DATE(2025,7,1) -> 45839 | B65: Europe | C65: 1219361.3 | D65: 780391.23 | E65: 438970.07 | F65: 0.64 | G65: 14345
A66: =DATE(2025,7,1) -> 45839 | B66: Asia Pacific | C66: 1125564.3 | D66: 922962.71 | E66: 202601.57 | F66: 0.82 | G66: 17316
A67: =DATE(2025,7,1) -> 45839 | B67: Other Markets | C67: 187594.05 | D67: 86293.261 | E67: 101300.79 | F67: 0.46 | G67: 2886
A68: =DATE(2025,8,1) -> 45870 | B68: North America | C68: 2200478.2 | D68: 1628353.8 | E68: 572124.32 | F68: 0.74 | G68: 25888
A69: =DATE(2025,8,1) -> 45870 | B69: Europe | C69: 1243748.5 | D69: 795999.06 | E69: 447749.47 | F69: 0.64 | G69: 14632
A70: =DATE(2025,8,1) -> 45870 | B70: Asia Pacific | C70: 1148075.6 | D70: 941421.96 | E70: 206653.6 | F70: 0.82 | G70: 17663
A71: =DATE(2025,8,1) -> 45870 | B71: Other Markets | C71: 191345.93 | D71: 88019.127 | E71: 103326.8 | F71: 0.46 | G71: 2944
A72: =DATE(2025,9,1) -> 45901 | B72: North America | C72: 2244487.7 | D72: 1660920.9 | E72: 583566.81 | F72: 0.74 | G72: 26406
A73: =DATE(2025,9,1) -> 45901 | B73: Europe | C73: 1268623.5 | D73: 811919.04 | E73: 456704.46 | F73: 0.64 | G73: 14925
A74: =DATE(2025,9,1) -> 45901 | B74: Asia Pacific | C74: 1171037.1 | D74: 960250.4 | E74: 210786.67 | F74: 0.82 | G74: 18016
A75: =DATE(2025,9,1) -> 45901 | B75: Other Markets | C75: 195172.85 | D75: 89779.509 | E75: 105393.34 | F75: 0.46 | G75: 3003
A76: =DATE(2025,10,1) -> 45931 | B76: North America | C76: 2289377.5 | D76: 1694139.3 | E76: 595238.15 | F76: 0.74 | G76: 26934
A77: =DATE(2025,10,1) -> 45931 | B77: Europe | C77: 1293996 | D77: 828157.42 | E77: 465838.55 | F77: 0.64 | G77: 15223
A78: =DATE(2025,10,1) -> 45931 | B78: Asia Pacific | C78: 1194457.8 | D78: 979455.41 | E78: 215002.41 | F78: 0.82 | G78: 18376
A79: =DATE(2025,10,1) -> 45931 | B79: Other Markets | C79: 199076.3 | D79: 91575.099 | E79: 107501.2 | F79: 0.46 | G79: 3063

Sheet Monthly Financial Data
A1: ZAVA SMART FABRIC & ATHLETIC WEAR - 2025 YTD SALES REPORT
A3: Month | B3: Revenue ($) | C3: COGS ($) | D3: Gross Profit ($) | E3: Gross Margin (%) | F3: OPEX ($) | G3: Net Profit ($) | H3: Notes
A4: Jan 2024 | B4: 4000000 | C4: 2240000 | D4: 1760000 | E4: 0.44 | F4: 1040000 | G4: 720000
A5: Feb 2024 | B5: 4060000 | C5: 2273600 | D5: 1786400 | E5: 0.44 | F5: 1055600 | G5: 730800
A6: Mar 2024 | B6: 4120900 | C6: 2307704 | D6: 1813196 | E6: 0.44 | F6: 1071434 | G6: 741762
A7: Apr 2024 | B7: 4182713 | C7: 2342319 | D7: 1840394 | E7: 0.44000007 | F7: 1087505 | G7: 752889
A8: May 2024 | B8: 4245454 | C8: 2377454 | D8: 1868000 | E8: 0.44000006 | F8: 1103818 | G8: 764182
A9: Jun 2024 | B9: 4309136 | C9: 2413116 | D9: 1896020 | E9: 0.44000004 | F9: 1120375 | G9: 775645
A10: Jul 2024 | B10: 4373773 | C10: 2449313 | D10: 1924460 | E10: 0.43999997 | F10: 1137181 | G10: 787279
A11: Aug 2024 | B11: 4439380 | C11: 2486053 | D11: 1953327 | E11: 0.43999995 | F11: 1154239 | G11: 799088
A12: Sep 2024 | B12: 4731269 | C12: 2554885 | D12: 2176384 | E12: 0.46000005 | F12: 1230130 | G12: 946254 | H12: Launch: Zava Smart Fiber v1
A13: Oct 2024 | B13: 4802238 | C13: 2593209 | D13: 2209029 | E13: 0.4599999 | F13: 1248582 | G13: 960447
A14: Nov 2024 | B14: 5751640 | C14: 3105886 | D14: 2645754 | E14: 0.45999993 | F14: 1495426 | G14: 1150328 | H14: Holiday spike
A15: Dec 2024 | B15: 6678970 | C15: 3606644 | D15: 3072326 | E15: 0.45999997 | F15: 1736532 | G15: 1335794 | H15: Holiday peak
A16: =DATE(2025,1,1) -> 45658 | B16: 3808346.1 | C16: 2056506.9 | D16: 1751839.2 | E16: 0.46 | F16: 990170 | G16: 761669.23
A17: =DATE(2025,2,1) -> 45689 | B17: 3868571 | C17: 2089028.4 | D17: 1779542.7 | E17: 0.46 | F17: 1005828.5 | G17: 773714.21
A18: =DATE(2025,3,1) -> 45717 | B18: 4332697.5 | C18: 2339656.7 | D18: 1993040.9 | E18: 0.46 | F18: 1126501.4 | G18: 866539.51 | H18: Marketing campaign launched for Smart Fiber
A19: =DATE(2025,4,1) -> 45748 | B19: 4419351.5 | C19: 2386449.8 | D19: 2032901.7 | E19: 0.46 | F19: 1149031.4 | G19: 883870.3
A20: =DATE(2025,5,1) -> 45778 | B20: 4507738.5 | C20: 2434178.8 | D20: 2073559.7 | E20: 0.46 | F20: 1172012 | G20: 901547.71
A21: =DATE(2025,6,1) -> 45809 | B21: 4597893.3 | C21: 2482862.4 | D21: 2115030.9 | E21: 0.46 | F21: 1195452.3 | G21: 919578.66
A22: =DATE(2025,7,1) -> 45839 | B22: 4689851.2 | C22: 2532519.6 | D22: 2157331.5 | E22: 0.46 | F22: 1219361.3 | G22: 937970.23
A23: =DATE(2025,8,1) -> 45870 | B23: 4783648.2 | C23: 2583170 | D23: 2200478.2 | E23: 0.46 | F23: 1243748.5 | G23: 956729.64
A24: =DATE(2025,9,1) -> 45901 | B24: 4879321.2 | C24: 2634833.4 | D24: 2244487.7 | E24: 0.46 | F24: 1268623.5 | G24: 975864.23
A25: =DATE(2025,10,1) -> 45931 | B25: 4976907.6 | C25: 2687530.1 | D25: 2289377.5 | E25: 0.46 | F25: 1293996 | G25: 995381.52

Sheet Executive Dashboard
A1: ZAVA SMART FABRIC & ATHLETIC WEAR — 2025 YTD EXECUTIVE DASHBOARD
A2: Period: January 2025 – October 2025 | Data Sources: Product Categories, Regional Sales, Monthly Financial Data
A3: Total 2025 YTD Revenue | D3: Total 2025 YTD Net Profit | G3: Avg Gross Margin | J3: Total 2025 Units Sold | M3: Total 2025 Customers
A4: =SUM('Monthly Financial Data'!B16:B25) -> 44864326 | D4: =SUM('Monthly Financial Data'!G16:G25) -> 8972865.2 | G4: =AVERAGE('Monthly Financial Data'!E16:E25) -> 0.46 | J4: =SUM('Product Categories'!D43:D172) -> 744799 | M4: =SUM('Regional Sales'!G40:G79) -> 573290
A6: MONTHLY REVENUE & PROFIT TREND (2025) | H6: REVENUE BY REGION (2025 YTD)
A7: Month | B7: Revenue ($) | C7: COGS ($) | D7: Gross Profit ($) | E7: Net Profit ($) | F7: Gross Margin | H7: Region | I7: Total Revenue ($) | J7: Smart Fabric Rev ($) | K7: Traditional Rev ($) | L7: Smart Fabric % | M7: Total Customers | N7: % of Revenue
A8: 45658 | B8: ='Monthly Financial Data'!B16 -> 3808346.1 | C8: ='Monthly Financial Data'!C16 -> 2056506.9 | D8: ='Monthly Financial Data'!D16 -> 1751839.2 | E8: ='Monthly Financial Data'!G16 -> 761669.23 | F8: ='Monthly Financial Data'!E16 -> 0.46 | H8: North America | I8: =SUMIFS('Regional Sales'!C4:C79,'Regional Sales'!B4:B79,H8,'Regional Sales'!A4:A79,">="&DATE(2025,1,1)) -> 20637590 | J8: =SUMIFS('Regional Sales'!D4:D79,'Regional Sales'!B4:B79,H8,'Regional Sales'!A4:A79,">="&DATE(2025,1,1)) -> 15271817 | K8: =SUMIFS('Regional Sales'!E4:E79,'Regional Sales'!B4:B79,H8,'Regional Sales'!A4:A79,">="&DATE(2025,1,1)) -> 5365773.4 | L8: =IF(I8=0,"",J8/I8) -> 0.74 | M8: =SUMIFS('Regional Sales'!G4:G79,'Regional Sales'!B4:B79,H8,'Regional Sales'!A4:A79,">="&DATE(2025,1,1)) -> 242796 | N8: =IF(SUM(I8:I11)=0,"",I8/SUM(I8:I11)) -> 0.46
A9: 45689 | B9: ='Monthly Financial Data'!B17 -> 3868571 | C9: ='Monthly Financial Data'!C17 -> 2089028.4 | D9: ='Monthly Financial Data'!D17 -> 1779542.7 | E9: ='Monthly Financial Data'!G17 -> 773714.21 | F9: ='Monthly Financial Data'!E17 -> 0.46 | H9: Europe | I9: =SUMIFS('Regional Sales'!C4:C79,'Regional Sales'!B4:B79,H9,'Regional Sales'!A4:A79,">="&DATE(2025,1,1)) -> 11664725 | J9: =SUMIFS('Regional Sales'!D4:D79,'Regional Sales'!B4:B79,H9,'Regional Sales'!A4:A79,">="&DATE(2025,1,1)) -> 7465423.9 | K9: =SUMIFS('Regional Sales'!E4:E79,'Regional Sales'!B4:B79,H9,'Regional Sales'!A4:A79,">="&DATE(2025,1,1)) -> 4199300.9 | L9: =IF(I9=0,"",J9/I9) -> 0.64 | M9: =SUMIFS('Regional Sales'!G4:G79,'Regional Sales'!B4:B79,H9,'Regional Sales'!A4:A79,">="&DATE(2025,1,1)) -> 137230 | N9: =IF(SUM(I8:I11)=0,"",I9/SUM(I8:I11)) -> 0.26
A10: 45717 | B10: ='Monthly Financial Data'!B18 -> 4332697.5 | C10: ='Monthly Financial Data'!C18 -> 2339656.7 | D10: ='Monthly Financial Data'!D18 -> 1993040.9 | E10: ='Monthly Financial Data'!G18 -> 866539.51 | F10: ='Monthly Financial Data'!E18 -> 0.46 | H10: Asia Pacific | I10: =SUMIFS('Regional Sales'!C4:C79,'Regional Sales'!B4:B79,H10,'Regional Sales'!A4:A79,">="&DATE(2025,1,1)) -> 10767438 | J10: =SUMIFS('Regional Sales'!D4:D79,'Regional Sales'!B4:B79,H10,'Regional Sales'!A4:A79,">="&DATE(2025,1,1)) -> 8829299.4 | K10: =SUMIFS('Regional Sales'!E4:E79,'Regional Sales'!B4:B79,H10,'Regional Sales'!A4:A79,">="&DATE(2025,1,1)) -> 1938138.9 | L10: =IF(I10=0,"",J10/I10) -> 0.82 | M10: =SUMIFS('Regional Sales'!G4:G79,'Regional Sales'!B4:B79,H10,'Regional Sales'!A4:A79,">="&DATE(2025,1,1)) -> 165654 | N10: =IF(SUM(I8:I11)=0,"",I10/SUM(I8:I11)) -> 0.24
A11: 45748 | B11: ='Monthly Financial Data'!B19 -> 4419351.5 | C11: ='Monthly Financial Data'!C19 -> 2386449.8 | D11: ='Monthly Financial Data'!D19 -> 2032901.7 | E11: ='Monthly Financial Data'!G19 -> 883870.3 | F11: ='Monthly Financial Data'!E19 -> 0.46 | H11: Other Markets | I11: =SUMIFS('Regional Sales'!C4:C79,'Regional Sales'!B4:B79,H11,'Regional Sales'!A4:A79,">="&DATE(2025,1,1)) -> 1794573 | J11: =SUMIFS('Regional Sales'!D4:D79,'Regional Sales'!B4:B79,H11,'Regional Sales'!A4:A79,">="&DATE(2025,1,1)) -> 825503.6 | K11: =SUMIFS('Regional Sales'!E4:E79,'Regional Sales'!B4:B79,H11,'Regional Sales'!A4:A79,">="&DATE(2025,1,1)) -> 969069.44 | L11: =IF(I11=0,"",J11/I11) -> 0.46 | M11: =SUMIFS('Regional Sales'!G4:G79,'Regional Sales'!B4:B79,H11,'Regional Sales'!A4:A79,">="&DATE(2025,1,1)) -> 27610 | N11: =IF(SUM(I8:I11)=0,"",I11/SUM(I8:I11)) -> 0.04
A12: 45778 | B12: ='Monthly Financial Data'!B20 -> 4507738.5 | C12: ='Monthly Financial Data'!C20 -> 2434178.8 | D12: ='Monthly Financial Data'!D20 -> 2073559.7 | E12: ='Monthly Financial Data'!G20 -> 901547.71 | F12: ='Monthly Financial Data'!E20 -> 0.46 | H12: TOTAL | I12: =SUM(I8:I11) -> 44864326 | J12: =SUM(J8:J11) -> 32392043 | K12: =SUM(K8:K11) -> 12472283 | L12: =IF(I12=0,"",J12/I12) -> 0.722 | M12: =SUM(M8:M11) -> 573290 | N12: 1
A13: 45809 | B13: ='Monthly Financial Data'!B21 -> 4597893.3 | C13: ='Monthly Financial Data'!C21 -> 2482862.4 | D13: ='Monthly Financial Data'!D21 -> 2115030.9 | E13: ='Monthly Financial Data'!G21 -> 919578.66 | F13: ='Monthly Financial Data'!E21 -> 0.46
A14: 45839 | B14: ='Monthly Financial Data'!B22 -> 4689851.2 | C14: ='Monthly Financial Data'!C22 -> 2532519.6 | D14: ='Monthly Financial Data'!D22 -> 2157331.5 | E14: ='Monthly Financial Data'!G22 -> 937970.23 | F14: ='Monthly Financial Data'!E22 -> 0.46
A15: 45870 | B15: ='Monthly Financial Data'!B23 -> 4783648.2 | C15: ='Monthly Financial Data'!C23 -> 2583170 | D15: ='Monthly Financial Data'!D23 -> 2200478.2 | E15: ='Monthly Financial Data'!G23 -> 956729.64 | F15: ='Monthly Financial Data'!E23 -> 0.46
A16: 45901 | B16: ='Monthly Financial Data'!B24 -> 4879321.2 | C16: ='Monthly Financial Data'!C24 -> 2634833.4 | D16: ='Monthly Financial Data'!D24 -> 2244487.7 | E16: ='Monthly Financial Data'!G24 -> 975864.23 | F16: ='Monthly Financial Data'!E24 -> 0.46
A17: 45931 | B17: ='Monthly Financial Data'!B25 -> 4976907.6 | C17: ='Monthly Financial Data'!C25 -> 2687530.1 | D17: ='Monthly Financial Data'!D25 -> 2289377.5 | E17: ='Monthly Financial Data'!G25 -> 995381.52 | F17: ='Monthly Financial Data'!E25 -> 0.46
A18: TOTAL / AVG | B18: =SUM(B8:B17) -> 44864326 | C18: =SUM(C8:C17) -> 24226736 | D18: =SUM(D8:D17) -> 20637590 | E18: =SUM(E8:E17) -> 8972865.2 | F18: =AVERAGE(F8:F17) -> 0.46
A20: PRODUCT PERFORMANCE (2025 YTD) | I20: SMART FABRIC vs TRADITIONAL (2025 YTD)
A21: Product | B21: Category | C21: Total Units Sold | D21: Total Revenue ($) | E21: Total Gross Profit ($) | F21: Avg Unit Price ($) | G21: % of Total Revenue | I21: Metric | J21: Smart Fabric | K21: Traditional | L21: SF % Share | M21: Trad % Share | N21: Grand Total
A22: Smart Athletic Shirts | B22: Smart Fabric | C22: =SUMIFS('Product Categories'!D43:D172,'Product Categories'!C43:C172,A22) -> 45653 | D22: =SUMIFS('Product Categories'!F43:F172,'Product Categories'!C43:C172,A22) -> 6288478.3 | E22: =SUMIFS('Product Categories'!G43:G172,'Product Categories'!C43:C172,A22) -> 3270008.7 | F22: =IFERROR(D22/C22,0) -> 137.74513 | G22: =IFERROR(D22/SUM(D22:D34),0) -> 0.14016656 | I22: Units Sold | J22: =SUMIFS('Product Categories'!D43:D172,'Product Categories'!B43:B172,"Smart Fabric") -> 264524 | K22: =SUMIFS('Product Categories'!D43:D172,'Product Categories'!B43:B172,"Traditional Athletic Wear") -> 480275 | L22: =IFERROR(J22/(J22+K22),0) -> 0.35516159 | M22: =IFERROR(K22/(J22+K22),0) -> 0.64483841 | N22: =J22+K22 -> 744799
A23: Performance Monitoring Leggings | B23: Smart Fabric | C23: =SUMIFS('Product Categories'!D43:D172,'Product Categories'!C43:C172,A23) -> 29668 | D23: =SUMIFS('Product Categories'!F43:F172,'Product Categories'!C43:C172,A23) -> 5029748.7 | E23: =SUMIFS('Product Categories'!G43:G172,'Product Categories'!C43:C172,A23) -> 2615469.3 | F23: =IFERROR(D23/C23,0) -> 169.53447 | G23: =IFERROR(D23/SUM(D22:D34),0) -> 0.1121102 | I23: Revenue ($) | J23: =SUMIFS('Product Categories'!F43:F172,'Product Categories'!B43:B172,"Smart Fabric") -> 31320345 | K23: =SUMIFS('Product Categories'!F43:F172,'Product Categories'!B43:B172,"Traditional Athletic Wear") -> 13543981 | L23: =IFERROR(J23/(J23+K23),0) -> 0.69811246 | M23: =IFERROR(K23/(J23+K23),0) -> 0.30188754 | N23: =J23+K23 -> 44864326
A24: Temperature-Regulating Shorts | B24: Smart Fabric | C24: =SUMIFS('Product Categories'!D43:D172,'Product Categories'!C43:C172,A24) -> 47480 | D24: =SUMIFS('Product Categories'!F43:F172,'Product Categories'!C43:C172,A24) -> 4527635.1 | E24: =SUMIFS('Product Categories'!G43:G172,'Product Categories'!C43:C172,A24) -> 2354370.2 | F24: =IFERROR(D24/C24,0) -> 95.358784 | G24: =IFERROR(D24/SUM(D22:D34),0) -> 0.10091838 | I24: Gross Profit ($) | J24: =SUMIFS('Product Categories'!G43:G172,'Product Categories'!B43:B172,"Smart Fabric") -> 16654037 | K24: =SUMIFS('Product Categories'!G43:G172,'Product Categories'!B43:B172,"Traditional Athletic Wear") -> 4875833.2 | L24: =IFERROR(J24/(J24+K24),0) -> 0.77353169 | M24: =IFERROR(K24/(J24+K24),0) -> 0.22646831 | N24: =J24+K24 -> 21529870
A25: Biometric Sports Bras | B25: Smart Fabric | C25: =SUMIFS('Product Categories'!D43:D172,'Product Categories'!C43:C172,A25) -> 44511 | D25: =SUMIFS('Product Categories'!F43:F172,'Product Categories'!C43:C172,A25) -> 3772842.3 | E25: =SUMIFS('Product Categories'!G43:G172,'Product Categories'!C43:C172,A25) -> 1961878 | F25: =IFERROR(D25/C25,0) -> 84.76202 | G25: =IFERROR(D25/SUM(D22:D34),0) -> 0.084094482 | I25: Avg Unit Price ($) | J25: =IFERROR(J23/J22,0) -> 118.40266 | K25: =IFERROR(K23/K22,0) -> 28.200471 | L25: — | M25: — | N25: =IFERROR(N23/N22,0) -> 60.236824
A26: Zava Smart Fiber | B26: Smart Fabric | C26: =SUMIFS('Product Categories'!D43:D172,'Product Categories'!C43:C172,A26) -> 37857 | D26: =SUMIFS('Product Categories'!F43:F172,'Product Categories'!C43:C172,A26) -> 9186431.7 | E26: =SUMIFS('Product Categories'!G43:G172,'Product Categories'!C43:C172,A26) -> 5144401.7 | F26: =IFERROR(D26/C26,0) -> 242.66137 | G26: =IFERROR(D26/SUM(D22:D34),0) -> 0.20476027 | I26: Profit Margin (%) | J26: =IFERROR(J24/J23,0) -> 0.53173222 | K26: =IFERROR(K24/K23,0) -> 0.36 | L26: — | M26: — | N26: =IFERROR(N24/N23,0) -> 0.4798884
A27: AI-Enhanced Running Socks | B27: Smart Fabric | C27: =SUMIFS('Product Categories'!D43:D172,'Product Categories'!C43:C172,A27) -> 59355 | D27: =SUMIFS('Product Categories'!F43:F172,'Product Categories'!C43:C172,A27) -> 2515209.2 | E27: =SUMIFS('Product Categories'!G43:G172,'Product Categories'!C43:C172,A27) -> 1307908.8 | F27: =IFERROR(D27/C27,0) -> 42.375692 | G27: =IFERROR(D27/SUM(D22:D34),0) -> 0.056062565
A28: Basic Athletic Shirts | B28: Traditional Athletic Wear | C28: =SUMIFS('Product Categories'!D43:D172,'Product Categories'!C43:C172,A28) -> 85240 | D28: =SUMIFS('Product Categories'!F43:F172,'Product Categories'!C43:C172,A28) -> 2708853.9 | E28: =SUMIFS('Product Categories'!G43:G172,'Product Categories'!C43:C172,A28) -> 975187.41 | F28: =IFERROR(D28/C28,0) -> 31.77914 | G28: =IFERROR(D28/SUM(D22:D34),0) -> 0.060378794 | I28: TOP PRODUCTS BY REVENUE (2025 YTD)
A29: Standard Leggings | B29: Traditional Athletic Wear | C29: =SUMIFS('Product Categories'!D43:D172,'Product Categories'!C43:C172,A29) -> 46024 | D29: =SUMIFS('Product Categories'!F43:F172,'Product Categories'!C43:C172,A29) -> 2438001.5 | E29: =SUMIFS('Product Categories'!G43:G172,'Product Categories'!C43:C172,A29) -> 877680.54 | F29: =IFERROR(D29/C29,0) -> 52.972395 | G29: =IFERROR(D29/SUM(D22:D34),0) -> 0.05434165 | I29: Rank | J29: Product | K29: Category | L29: Revenue ($) | M29: Units Sold | N29: % of Revenue
A30: Athletic Shorts | B30: Traditional Athletic Wear | C30: =SUMIFS('Product Categories'!D43:D172,'Product Categories'!C43:C172,A30) -> 54791 | D30: =SUMIFS('Product Categories'!F43:F172,'Product Categories'!C43:C172,A30) -> 2031509.2 | E30: =SUMIFS('Product Categories'!G43:G172,'Product Categories'!C43:C172,A30) -> 731343.3 | F30: =IFERROR(D30/C30,0) -> 37.077424 | G30: =IFERROR(D30/SUM(D22:D34),0) -> 0.04528117 | I30: 1 | J30: =INDEX(A22:A34,MATCH(L30,D22:D34,0)) -> Zava Smart Fiber | K30: =INDEX(B22:B34,MATCH(L30,D22:D34,0)) -> Smart Fabric | L30: =LARGE(D22:D34,1) -> 9186431.7 | M30: =INDEX(C22:C34,MATCH(L30,D22:D34,0)) -> 37857 | N30: =IFERROR(L30/SUM(D22:D34),0) -> 0.20476027
A31: Sports Bras | B31: Traditional Athletic Wear | C31: =SUMIFS('Product Categories'!D43:D172,'Product Categories'!C43:C172,A31) -> 61376 | D31: =SUMIFS('Product Categories'!F43:F172,'Product Categories'!C43:C172,A31) -> 1625290.3 | E31: =SUMIFS('Product Categories'!G43:G172,'Product Categories'!C43:C172,A31) -> 585104.52 | F31: =IFERROR(D31/C31,0) -> 26.480878 | G31: =IFERROR(D31/SUM(D22:D34),0) -> 0.036226786 | I31: 2 | J31: =INDEX(A22:A34,MATCH(L31,D22:D34,0)) -> Smart Athletic Shirts | K31: =INDEX(B22:B34,MATCH(L31,D22:D34,0)) -> Smart Fabric | L31: =LARGE(D22:D34,2) -> 6288478.3 | M31: =INDEX(C22:C34,MATCH(L31,D22:D34,0)) -> 45653 | N31: =IFERROR(L31/SUM(D22:D34),0) -> 0.14016656
A32: Compression Wear | B32: Traditional Athletic Wear | C32: =SUMIFS('Product Categories'!D43:D172,'Product Categories'!C43:C172,A32) -> 21303 | D32: =SUMIFS('Product Categories'!F43:F172,'Product Categories'!C43:C172,A32) -> 1354206.6 | E32: =SUMIFS('Product Categories'!G43:G172,'Product Categories'!C43:C172,A32) -> 487514.38 | F32: =IFERROR(D32/C32,0) -> 63.568822 | G32: =IFERROR(D32/SUM(D22:D34),0) -> 0.030184486 | I32: 3 | J32: =INDEX(A22:A34,MATCH(L32,D22:D34,0)) -> Performance Monitoring Leggings | K32: =INDEX(B22:B34,MATCH(L32,D22:D34,0)) -> Smart Fabric | L32: =LARGE(D22:D34,3) -> 5029748.7 | M32: =INDEX(C22:C34,MATCH(L32,D22:D34,0)) -> 29668 | N32: =IFERROR(L32/SUM(D22:D34),0) -> 0.1121102
A33: Athletic Socks | B33: Traditional Athletic Wear | C33: =SUMIFS('Product Categories'!D43:D172,'Product Categories'!C43:C172,A33) -> 147603 | D33: =SUMIFS('Product Categories'!F43:F172,'Product Categories'!C43:C172,A33) -> 2031749.6 | E33: =SUMIFS('Product Categories'!G43:G172,'Product Categories'!C43:C172,A33) -> 731429.87 | F33: =IFERROR(D33/C33,0) -> 13.764962 | G33: =IFERROR(D33/SUM(D22:D34),0) -> 0.04528653 | I33: 4 | J33: =INDEX(A22:A34,MATCH(L33,D22:D34,0)) -> Temperature-Regulating Shorts | K33: =INDEX(B22:B34,MATCH(L33,D22:D34,0)) -> Smart Fabric | L33: =LARGE(D22:D34,4) -> 4527635.1 | M33: =INDEX(C22:C34,MATCH(L33,D22:D34,0)) -> 47480 | N33: =IFERROR(L33/SUM(D22:D34),0) -> 0.10091838
A34: Accessories & Equipment | B34: Traditional Athletic Wear | C34: =SUMIFS('Product Categories'!D43:D172,'Product Categories'!C43:C172,A34) -> 63938 | D34: =SUMIFS('Product Categories'!F43:F172,'Product Categories'!C43:C172,A34) -> 1354369.8 | E34: =SUMIFS('Product Categories'!G43:G172,'Product Categories'!C43:C172,A34) -> 487573.13 | F34: =IFERROR(D34/C34,0) -> 21.182549 | G34: =IFERROR(D34/SUM(D22:D34),0) -> 0.030188123 | I34: 5 | J34: =INDEX(A22:A34,MATCH(L34,D22:D34,0)) -> Biometric Sports Bras | K34: =INDEX(B22:B34,MATCH(L34,D22:D34,0)) -> Smart Fabric | L34: =LARGE(D22:D34,5) -> 3772842.3 | M34: =INDEX(C22:C34,MATCH(L34,D22:D34,0)) -> 44511 | N34: =IFERROR(L34/SUM(D22:D34),0) -> 0.084094482
A35: TOTAL | C35: =SUM(C22:C34) -> 744799 | D35: =SUM(D22:D34) -> 44864326 | E35: =SUM(E22:E34) -> 21529870 | F35: =IFERROR(D35/C35,0) -> 60.236824 | G35: 1 | I35: 6 | J35: =INDEX(A22:A34,MATCH(L35,D22:D34,0)) -> Basic Athletic Shirts | K35: =INDEX(B22:B34,MATCH(L35,D22:D34,0)) -> Traditional Athletic Wear | L35: =LARGE(D22:D34,6) -> 2708853.9 | M35: =INDEX(C22:C34,MATCH(L35,D22:D34,0)) -> 85240 | N35: =IFERROR(L35/SUM(D22:D34),0) -> 0.060378794
I36: 7 | J36: =INDEX(A22:A34,MATCH(L36,D22:D34,0)) -> AI-Enhanced Running Socks | K36: =INDEX(B22:B34,MATCH(L36,D22:D34,0)) -> Smart Fabric | L36: =LARGE(D22:D34,7) -> 2515209.2 | M36: =INDEX(C22:C34,MATCH(L36,D22:D34,0)) -> 59355 | N36: =IFERROR(L36/SUM(D22:D34),0) -> 0.056062565
A37: MONTHLY REVENUE BY REGION (2025) | I37: 8 | J37: =INDEX(A22:A34,MATCH(L37,D22:D34,0)) -> Standard Leggings | K37: =INDEX(B22:B34,MATCH(L37,D22:D34,0)) -> Traditional Athletic Wear | L37: =LARGE(D22:D34,8) -> 2438001.5 | M37: =INDEX(C22:C34,MATCH(L37,D22:D34,0)) -> 46024 | N37: =IFERROR(L37/SUM(D22:D34),0) -> 0.05434165
A38: Month | B38: North America | C38: Europe | D38: Asia Pacific | E38: Other Markets | F38: Total | I38: 9 | J38: =INDEX(A22:A34,MATCH(L38,D22:D34,0)) -> Athletic Socks | K38: =INDEX(B22:B34,MATCH(L38,D22:D34,0)) -> Traditional Athletic Wear | L38: =LARGE(D22:D34,9) -> 2031749.6 | M38: =INDEX(C22:C34,MATCH(L38,D22:D34,0)) -> 147603 | N38: =IFERROR(L38/SUM(D22:D34),0) -> 0.04528653
A39: 45658 | B39: ='Regional Sales'!C40 -> 1751839.2 | C39: ='Regional Sales'!C41 -> 990170 | D39: ='Regional Sales'!C42 -> 914003.08 | E39: ='Regional Sales'!C43 -> 152333.85 | F39: =SUM(B39:E39) -> 3808346.1 | I39: 10 | J39: =INDEX(A22:A34,MATCH(L39,D22:D34,0)) -> Athletic Shorts | K39: =INDEX(B22:B34,MATCH(L39,D22:D34,0)) -> Traditional Athletic Wear | L39: =LARGE(D22:D34,10) -> 2031509.2 | M39: =INDEX(C22:C34,MATCH(L39,D22:D34,0)) -> 54791 | N39: =IFERROR(L39/SUM(D22:D34),0) -> 0.04528117
A40: 45689 | B40: ='Regional Sales'!C44 -> 1779542.7 | C40: ='Regional Sales'!C45 -> 1005828.5 | D40: ='Regional Sales'!C46 -> 928457.05 | E40: ='Regional Sales'!C47 -> 154742.84 | F40: =SUM(B40:E40) -> 3868571 | I40: 11 | J40: =INDEX(A22:A34,MATCH(L40,D22:D34,0)) -> Sports Bras | K40: =INDEX(B22:B34,MATCH(L40,D22:D34,0)) -> Traditional Athletic Wear | L40: =LARGE(D22:D34,11) -> 1625290.3 | M40: =INDEX(C22:C34,MATCH(L40,D22:D34,0)) -> 61376 | N40: =IFERROR(L40/SUM(D22:D34),0) -> 0.036226786
A41: 45717 | B41: ='Regional Sales'!C48 -> 1993040.9 | C41: ='Regional Sales'!C49 -> 1126501.4 | D41: ='Regional Sales'!C50 -> 1039847.4 | E41: ='Regional Sales'!C51 -> 173307.9 | F41: =SUM(B41:E41) -> 4332697.5 | I41: 12 | J41: =INDEX(A22:A34,MATCH(L41,D22:D34,0)) -> Accessories & Equipment | K41: =INDEX(B22:B34,MATCH(L41,D22:D34,0)) -> Traditional Athletic Wear | L41: =LARGE(D22:D34,12) -> 1354369.8 | M41: =INDEX(C22:C34,MATCH(L41,D22:D34,0)) -> 63938 | N41: =IFERROR(L41/SUM(D22:D34),0) -> 0.030188123
A42: 45748 | B42: ='Regional Sales'!C52 -> 2032901.7 | C42: ='Regional Sales'!C53 -> 1149031.4 | D42: ='Regional Sales'!C54 -> 1060644.4 | E42: ='Regional Sales'!C55 -> 176774.06 | F42: =SUM(B42:E42) -> 4419351.5 | I42: 13 | J42: =INDEX(A22:A34,MATCH(L42,D22:D34,0)) -> Compression Wear | K42: =INDEX(B22:B34,MATCH(L42,D22:D34,0)) -> Traditional Athletic Wear | L42: =LARGE(D22:D34,13) -> 1354206.6 | M42: =INDEX(C22:C34,MATCH(L42,D22:D34,0)) -> 21303 | N42: =IFERROR(L42/SUM(D22:D34),0) -> 0.030184486
A43: 45778 | B43: ='Regional Sales'!C56 -> 2073559.7 | C43: ='Regional Sales'!C57 -> 1172012 | D43: ='Regional Sales'!C58 -> 1081857.2 | E43: ='Regional Sales'!C59 -> 180309.54 | F43: =SUM(B43:E43) -> 4507738.5
A44: 45809 | B44: ='Regional Sales'!C60 -> 2115030.9 | C44: ='Regional Sales'!C61 -> 1195452.3 | D44: ='Regional Sales'!C62 -> 1103494.4 | E44: ='Regional Sales'!C63 -> 183915.73 | F44: =SUM(B44:E44) -> 4597893.3
A45: 45839 | B45: ='Regional Sales'!C64 -> 2157331.5 | C45: ='Regional Sales'!C65 -> 1219361.3 | D45: ='Regional Sales'!C66 -> 1125564.3 | E45: ='Regional Sales'!C67 -> 187594.05 | F45: =SUM(B45:E45) -> 4689851.2
A46: 45870 | B46: ='Regional Sales'!C68 -> 2200478.2 | C46: ='Regional Sales'!C69 -> 1243748.5 | D46: ='Regional Sales'!C70 -> 1148075.6 | E46: ='Regional Sales'!C71 -> 191345.93 | F46: =SUM(B46:E46) -> 4783648.2
A47: 45901 | B47: ='Regional Sales'!C72 -> 2244487.7 | C47: ='Regional Sales'!C73 -> 1268623.5 | D47: ='Regional Sales'!C74 -> 1171037.1 | E47: ='Regional Sales'!C75 -> 195172.85 | F47: =SUM(B47:E47) -> 4879321.2
A48: 45931 | B48: ='Regional Sales'!C76 -> 2289377.5 | C48: ='Regional Sales'!C77 -> 1293996 | D48: ='Regional Sales'!C78 -> 1194457.8 | E48: ='Regional Sales'!C79 -> 199076.3 | F48: =SUM(B48:E48) -> 4976907.6
A49: TOTAL | B49: =SUM(B39:B48) -> 20637590 | C49: =SUM(C39:C48) -> 11664725 | D49: =SUM(D39:D48) -> 10767438 | E49: =SUM(E39:E48) -> 1794573 | F49: =SUM(F39:F48) -> 44864326
A51: VISUAL ANALYTICS
A70: Metric | B70: Smart Fabric | C70: Traditional | E70: Product | F70: Revenue ($M)
A71: Revenue ($M) | B71: =J23/1000000 -> 31.320345 | C71: =K23/1000000 -> 13.543981 | E71: =J30 -> Zava Smart Fiber | F71: =L30/1000000 -> 9.1864317
A72: Gross Profit ($M) | B72: =J24/1000000 -> 16.654037 | C72: =K24/1000000 -> 4.8758332 | E72: =J31 -> Smart Athletic Shirts | F72: =L31/1000000 -> 6.2884783
A73: Units Sold (K) | B73: =J22/1000 -> 264.524 | C73: =K22/1000 -> 480.275 | E73: =J32 -> Performance Monitoring Leggings | F73: =L32/1000000 -> 5.0297487
E74: =J33 -> Temperature-Regulating Shorts | F74: =L33/1000000 -> 4.5276351
E75: =J34 -> Biometric Sports Bras | F75: =L34/1000000 -> 3.7728423
A84: Note: All data is formula-driven from source sheets (Product Categories, Regional Sales, Monthly Financial Data). Smart Fabric includes 6 products; Traditional Athletic Wear includes 7 products.
